neotest/__init__.py
neotest/__main__.py
neotest/main.py
neotest/logging/__init__.py
neotest/logging/log.py
neotest-0.0.1.dev2.dist-info/AUTHORS
neotest-0.0.1.dev2.dist-info/LICENSE
neotest-0.0.1.dev2.dist-info/METADATA
neotest-0.0.1.dev2.dist-info/WHEEL
neotest-0.0.1.dev2.dist-info/entry_points.txt
neotest-0.0.1.dev2.dist-info/pbr.json
neotest-0.0.1.dev2.dist-info/top_level.txt
neotest-0.0.1.dev2.dist-info/RECORD
